[
    {
      "_id": "67989b429d7825e30ee86a32",
      "rollNumber": null,
      "email": "bgkcbe@gmail.com",
      "name": "Gokul Kumar Bhoomibalan",
      "yearOfGraduation": 2022,
      "programStudied": "BTech",
      "linkedinUrl": "https://www.linkedin.com/in/gokul-kumar-bhoomibalan-52aa86195",
      "job": "Software Development Engineer II at Amazon",
      "sector": "Private",
      "approval_status": "pending",
      "higherStudies": "No",
      "institutionName": null
    },
    {
      "_id": "67989b429d7825e30ee86a33",
      "rollNumber": null,
      "email": "annapoornakathreya@gmail.com",
      "name": "Annapoorna Athreya",
      "yearOfGraduation": 2022,
      "programStudied": "BTech",
      "linkedinUrl": "https://www.linkedin.com/in/poorna-athreya-79755123a",
      "job": "Software Engineer I at McKinsey & Company",
      "sector": "Private",
      "approval_status": "pending",
      "higherStudies": "No",
      "institutionName": null
    },
    {
      "_id": "67989b429d7825e30ee86a34",
      "rollNumber": null,
      "email": "riteshnirmal2000@gmail.com",
      "name": "Ritesh Nirmal R",
      "yearOfGraduation": 2022,
      "programStudied": "BTech",
      "linkedinUrl": "https://www.linkedin.com/in/ritesh-nirmal-r-5666b7163",
      "job": "Engineer at Schneider Electric",
      "sector": "Private",
      "approval_status": "pending",
      "higherStudies": "No",
      "institutionName": null
    },
    {
      "_id": "67989b429d7825e30ee86a35",
      "rollNumber": null,
      "email": "Sathishj8@gmail.com",
      "name": "Sathish J",
      "yearOfGraduation": 2015,
      "programStudied": "BTech",
      "linkedinUrl": "https://www.linkedin.com/in/sathishjayabalan",
      "job": "Principal Product Manager, ICICI Lombard",
      "sector": "Private",
      "approval_status": "pending",
      "higherStudies": "Yes",
      "institutionName": "Indian Institute of Management, Indore"
    },
    {
      "_id": "67989b429d7825e30ee86a36",
      "rollNumber": null,
      "email": "kaarthivijey@gmail.com",
      "name": "Karthi Vijayakumaar",
      "yearOfGraduation": 2022,
      "programStudied": "BTech",
      "linkedinUrl": "https://www.linkedin.com/in/karthi-vijayakumaar",
      "job": "Software Developer 2 at Oracle",
      "sector": "Private",
      "approval_status": "pending",
      "higherStudies": "No",
      "institutionName": null
    },
    {
      "_id": "67989b429d7825e30ee86a37",
      "rollNumber": null,
      "email": "abiramiap10@gmail.com",
      "name": "Abirami A P",
      "yearOfGraduation": 2022,
      "programStudied": "BTech",
      "linkedinUrl": "https://www.linkedin.com/in/abirami-a-p",
      "job": "Software Engineer at Ericsson",
      "sector": "Private",
      "approval_status": "pending",
      "higherStudies": "No",
      "institutionName": null
    },
    {
      "_id": "67989b429d7825e30ee86a38",
      "rollNumber": null,
      "email": "parthibansugumar66@gmail.com",
      "name": "Parthiban S",
      "yearOfGraduation": 2020,
      "programStudied": "BTech",
      "linkedinUrl": "https://www.linkedin.com/in/parthiban-sugumar-a93491147",
      "job": "Lead Software Engineer at Arcesium",
      "sector": "Private",
      "approval_status": "pending",
      "higherStudies": "No",
      "institutionName": null
    },
    {
      "_id": "67989b429d7825e30ee86a39",
      "rollNumber": null,
      "email": "akhilasasidharan5@gmail.com",
      "name": "Akhila P",
      "yearOfGraduation": 2019,
      "programStudied": "ME",
      "linkedinUrl": "https://www.linkedin.com/in/akhila-p-873a42183",
      "job": "Senior Software Engineer at Aptiv Technical Centre India",
      "sector": "Private",
      "approval_status": "pending",
      "higherStudies": "Yes",
      "institutionName": "PSG College of Technology"
    },
    {
      "_id": "67989b429d7825e30ee86a3a",
      "rollNumber": null,
      "email": "bhalmung@gmail.com",
      "name": "Mahendran Parameswaran",
      "yearOfGraduation": 2012,
      "programStudied": "BTech",
      "linkedinUrl": "https://www.linkedin.com/in/mahendranparameswaran",
      "job": "Software Developer at Inchcape Retail Limited",
      "sector": "Private",
      "approval_status": "pending",
      "higherStudies": "Yes",
      "institutionName": "University of Leicester"
    },
    {
      "_id": "67989b429d7825e30ee86a3b",
      "rollNumber": null,
      "email": "vaishnavee18102000@gmail.com",
      "name": "Vaishnavee R N",
      "yearOfGraduation": 2022,
      "programStudied": "BTech",
      "linkedinUrl": "https://www.linkedin.com/in/vaishnavee-r-n",
      "job": "Senior Systems Engineer at Infosys",
      "sector": "Private",
      "approval_status": "pending",
      "higherStudies": "No",
      "institutionName": null
    }
  ]
  